mensajes/__init__.py
mensajes/adios/__init__.py
mensajes/adios/despedidas.py
mensajes/hola/__init__.py
mensajes/hola/saludos.py
tests/__init__.py
tests/test_hola.py
Mensajes_jokin9-2.1.dist-info/METADATA
Mensajes_jokin9-2.1.dist-info/WHEEL
Mensajes_jokin9-2.1.dist-info/top_level.txt
Mensajes_jokin9-2.1.dist-info/RECORD
